{"name":"__dll__react","content":{"./node_modules/react/index.js":{"id":1,"buildMeta":{"providedExports":true}},"./node_modules/mobx/lib/mobx.module.js":{"id":2,"buildMeta":{"exportsType":"namespace","providedExports":["$mobx","FlowCancellationError","IDerivationState","ObservableMap","ObservableSet","Reaction","_allowStateChanges","_allowStateChangesInsideComputed","_allowStateReadsEnd","_allowStateReadsStart","_endAction","_getAdministration","_getGlobalState","_interceptReads","_isComputingDerivation","_resetGlobalState","_startAction","action","autorun","comparer","computed","configure","createAtom","decorate","entries","extendObservable","flow","get","getAtom","getDebugName","getDependencyTree","getObserverTree","has","intercept","isAction","isArrayLike","isBoxedObservable","isComputed","isComputedProp","isFlowCancellationError","isObservable","isObservableArray","isObservableMap","isObservableObject","isObservableProp","isObservableSet","keys","observable","observe","onBecomeObserved","onBecomeUnobserved","onReactionError","reaction","remove","runInAction","set","spy","toJS","trace","transaction","untracked","values","when"]}},"./node_modules/react-router/esm/react-router.js":{"id":9,"buildMeta":{"exportsType":"namespace","providedExports":["MemoryRouter","Prompt","Redirect","Route","Router","StaticRouter","Switch","__HistoryContext","__RouterContext","generatePath","matchPath","useHistory","useLocation","useParams","useRouteMatch","withRouter"]}},"./node_modules/@babel/runtime/helpers/esm/extends.js":{"id":13,"buildMeta":{"exportsType":"namespace","providedExports":["default"]}},"./node_modules/mobx-react-lite/dist/mobxreactlite.esm.js":{"id":14,"buildMeta":{"exportsType":"namespace","providedExports":["Observer","isObserverBatched","isUsingStaticRendering","observer","observerBatching","observerBatchingOptOut","useAsObservableSource","useForceUpdate","useLocalStore","useObserver","useStaticRendering"]}},"./node_modules/@babel/runtime/helpers/esm/inheritsLoose.js":{"id":19,"buildMeta":{"exportsType":"namespace","providedExports":["default"]}},"./node_modules/tiny-invariant/dist/tiny-invariant.esm.js":{"id":20,"buildMeta":{"exportsType":"namespace","providedExports":["default"]}},"./node_modules/lodash/isArray.js":{"id":24,"buildMeta":{"providedExports":true}},"./node_modules/history/esm/history.js":{"id":25,"buildMeta":{"exportsType":"namespace","providedExports":["createBrowserHistory","createHashHistory","createMemoryHistory","createLocation","locationsAreEqual","parsePath","createPath"]}},"./node_modules/lodash/_root.js":{"id":36,"buildMeta":{"providedExports":true}},"./node_modules/lodash/isObject.js":{"id":37,"buildMeta":{"providedExports":true}},"./node_modules/lodash/_baseGetTag.js":{"id":50,"buildMeta":{"providedExports":true}},"./node_modules/lodash/isObjectLike.js":{"id":51,"buildMeta":{"providedExports":true}},"./node_modules/lodash/_getNative.js":{"id":52,"buildMeta":{"providedExports":true}},"./node_modules/@babel/runtime/helpers/esm/objectWithoutPropertiesLoose.js":{"id":53,"buildMeta":{"exportsType":"namespace","providedExports":["default"]}},"./node_modules/webpack/buildin/global.js":{"id":60,"buildMeta":{"providedExports":true}},"./node_modules/process/browser.js":{"id":65,"buildMeta":{"providedExports":true}},"./node_modules/lodash/keys.js":{"id":66,"buildMeta":{"providedExports":true}},"./node_modules/lodash/isArrayLike.js":{"id":67,"buildMeta":{"providedExports":true}},"./node_modules/prop-types/index.js":{"id":68,"buildMeta":{"providedExports":true}},"./node_modules/lodash/isFunction.js":{"id":81,"buildMeta":{"providedExports":true}},"./node_modules/lodash/_Symbol.js":{"id":82,"buildMeta":{"providedExports":true}},"./node_modules/webpack/buildin/module.js":{"id":83,"buildMeta":{"providedExports":true}},"./node_modules/lodash/identity.js":{"id":84,"buildMeta":{"providedExports":true}},"./node_modules/lodash/_ListCache.js":{"id":85,"buildMeta":{"providedExports":true}},"./node_modules/lodash/_assocIndexOf.js":{"id":86,"buildMeta":{"providedExports":true}},"./node_modules/lodash/eq.js":{"id":87,"buildMeta":{"providedExports":true}},"./node_modules/lodash/_nativeCreate.js":{"id":88,"buildMeta":{"providedExports":true}},"./node_modules/lodash/_getMapData.js":{"id":89,"buildMeta":{"providedExports":true}},"./node_modules/lodash/isSymbol.js":{"id":90,"buildMeta":{"providedExports":true}},"./node_modules/lodash/_toKey.js":{"id":91,"buildMeta":{"providedExports":true}},"./node_modules/lodash/_isIndex.js":{"id":121,"buildMeta":{"providedExports":true}},"./node_modules/lodash/isLength.js":{"id":122,"buildMeta":{"providedExports":true}},"./node_modules/lodash/_Map.js":{"id":123,"buildMeta":{"providedExports":true}},"./node_modules/lodash/_MapCache.js":{"id":124,"buildMeta":{"providedExports":true}},"./node_modules/lodash/_isKey.js":{"id":125,"buildMeta":{"providedExports":true}},"./node_modules/lodash/_baseIndexOf.js":{"id":126,"buildMeta":{"providedExports":true}},"./node_modules/mini-create-react-context/dist/esm/index.js":{"id":127,"buildMeta":{"exportsType":"namespace","providedExports":["default"]}},"./node_modules/react-router/node_modules/path-to-regexp/index.js":{"id":128,"buildMeta":{"providedExports":true}},"./node_modules/object-assign/index.js":{"id":162,"buildMeta":{"providedExports":true}},"./node_modules/react-is/index.js":{"id":163,"buildMeta":{"providedExports":true}},"./node_modules/lodash/_freeGlobal.js":{"id":164,"buildMeta":{"providedExports":true}},"./node_modules/react-css-modules/dist/linkClass.js":{"id":165,"buildMeta":{"providedExports":true}},"./node_modules/lodash/forEach.js":{"id":166,"buildMeta":{"providedExports":true}},"./node_modules/lodash/_baseEach.js":{"id":167,"buildMeta":{"providedExports":true}},"./node_modules/lodash/isArguments.js":{"id":168,"buildMeta":{"providedExports":true}},"./node_modules/lodash/isBuffer.js":{"id":169,"buildMeta":{"providedExports":true}},"./node_modules/lodash/isTypedArray.js":{"id":170,"buildMeta":{"providedExports":true}},"./node_modules/lodash/_isPrototype.js":{"id":171,"buildMeta":{"providedExports":true}},"./node_modules/lodash/_arrayFilter.js":{"id":172,"buildMeta":{"providedExports":true}},"./node_modules/lodash/_Stack.js":{"id":173,"buildMeta":{"providedExports":true}},"./node_modules/lodash/_toSource.js":{"id":174,"buildMeta":{"providedExports":true}},"./node_modules/lodash/_baseIsEqual.js":{"id":175,"buildMeta":{"providedExports":true}},"./node_modules/lodash/_equalArrays.js":{"id":176,"buildMeta":{"providedExports":true}},"./node_modules/lodash/_isStrictComparable.js":{"id":177,"buildMeta":{"providedExports":true}},"./node_modules/lodash/_matchesStrictComparable.js":{"id":178,"buildMeta":{"providedExports":true}},"./node_modules/lodash/_baseGet.js":{"id":179,"buildMeta":{"providedExports":true}},"./node_modules/lodash/_castPath.js":{"id":180,"buildMeta":{"providedExports":true}},"./node_modules/lodash/toString.js":{"id":181,"buildMeta":{"providedExports":true}},"./node_modules/lodash/_baseToString.js":{"id":182,"buildMeta":{"providedExports":true}},"./node_modules/lodash/_arrayMap.js":{"id":183,"buildMeta":{"providedExports":true}},"./node_modules/react-css-modules/dist/renderNothing.js":{"id":184,"buildMeta":{"providedExports":true}},"./node_modules/lodash/_assignValue.js":{"id":185,"buildMeta":{"providedExports":true}},"./node_modules/lodash/_baseAssignValue.js":{"id":186,"buildMeta":{"providedExports":true}},"./node_modules/lodash/_defineProperty.js":{"id":187,"buildMeta":{"providedExports":true}},"./node_modules/hoist-non-react-statics/dist/hoist-non-react-statics.cjs.js":{"id":196,"buildMeta":{"providedExports":true}},"./node_modules/resolve-pathname/esm/resolve-pathname.js":{"id":197,"buildMeta":{"exportsType":"namespace","providedExports":["default"]}},"./node_modules/value-equal/esm/value-equal.js":{"id":198,"buildMeta":{"exportsType":"namespace","providedExports":["default"]}},"./node_modules/react/cjs/react.production.min.js":{"id":388,"buildMeta":{"providedExports":true}},"./node_modules/react-dom/index.js":{"id":389,"buildMeta":{"providedExports":true}},"./node_modules/react-dom/cjs/react-dom.production.min.js":{"id":390,"buildMeta":{"providedExports":true}},"./node_modules/scheduler/index.js":{"id":391,"buildMeta":{"providedExports":true}},"./node_modules/scheduler/cjs/scheduler.production.min.js":{"id":392,"buildMeta":{"providedExports":true}},"./node_modules/react-router-dom/esm/react-router-dom.js":{"id":393,"buildMeta":{"exportsType":"namespace","providedExports":["MemoryRouter","Prompt","Redirect","Route","Router","StaticRouter","Switch","generatePath","matchPath","useHistory","useLocation","useParams","useRouteMatch","withRouter","BrowserRouter","HashRouter","Link","NavLink"]}},"./node_modules/prop-types/factoryWithThrowingShims.js":{"id":394,"buildMeta":{"providedExports":true}},"./node_modules/prop-types/lib/ReactPropTypesSecret.js":{"id":395,"buildMeta":{"providedExports":true}},"./node_modules/react-router/node_modules/isarray/index.js":{"id":396,"buildMeta":{"providedExports":true}},"./node_modules/react-is/cjs/react-is.production.min.js":{"id":397,"buildMeta":{"providedExports":true}},"./node_modules/react-css-modules/dist/index.js":{"id":398,"buildMeta":{"providedExports":true}},"./node_modules/lodash/_getRawTag.js":{"id":399,"buildMeta":{"providedExports":true}},"./node_modules/lodash/_objectToString.js":{"id":400,"buildMeta":{"providedExports":true}},"./node_modules/react-css-modules/dist/extendReactClass.js":{"id":401,"buildMeta":{"providedExports":true}},"./node_modules/react-css-modules/node_modules/hoist-non-react-statics/dist/hoist-non-react-statics.cjs.js":{"id":402,"buildMeta":{"providedExports":true}},"./node_modules/lodash/_arrayEach.js":{"id":403,"buildMeta":{"providedExports":true}},"./node_modules/lodash/_baseForOwn.js":{"id":404,"buildMeta":{"providedExports":true}},"./node_modules/lodash/_baseFor.js":{"id":405,"buildMeta":{"providedExports":true}},"./node_modules/lodash/_createBaseFor.js":{"id":406,"buildMeta":{"providedExports":true}},"./node_modules/lodash/_arrayLikeKeys.js":{"id":407,"buildMeta":{"providedExports":true}},"./node_modules/lodash/_baseTimes.js":{"id":408,"buildMeta":{"providedExports":true}},"./node_modules/lodash/_baseIsArguments.js":{"id":409,"buildMeta":{"providedExports":true}},"./node_modules/lodash/stubFalse.js":{"id":410,"buildMeta":{"providedExports":true}},"./node_modules/lodash/_baseIsTypedArray.js":{"id":411,"buildMeta":{"providedExports":true}},"./node_modules/lodash/_baseUnary.js":{"id":412,"buildMeta":{"providedExports":true}},"./node_modules/lodash/_nodeUtil.js":{"id":413,"buildMeta":{"providedExports":true}},"./node_modules/lodash/_baseKeys.js":{"id":414,"buildMeta":{"providedExports":true}},"./node_modules/lodash/_nativeKeys.js":{"id":415,"buildMeta":{"providedExports":true}},"./node_modules/lodash/_overArg.js":{"id":416,"buildMeta":{"providedExports":true}},"./node_modules/lodash/_createBaseEach.js":{"id":417,"buildMeta":{"providedExports":true}},"./node_modules/lodash/_castFunction.js":{"id":418,"buildMeta":{"providedExports":true}},"./node_modules/object-unfreeze/dist/objectUnfreeze.js":{"id":419,"buildMeta":{"providedExports":true}},"./node_modules/react-css-modules/dist/isIterable.js":{"id":420,"buildMeta":{"providedExports":true}},"./node_modules/react-css-modules/dist/parseStyleName.js":{"id":421,"buildMeta":{"providedExports":true}},"./node_modules/lodash/filter.js":{"id":422,"buildMeta":{"providedExports":true}},"./node_modules/lodash/_baseFilter.js":{"id":423,"buildMeta":{"providedExports":true}},"./node_modules/lodash/_baseIteratee.js":{"id":424,"buildMeta":{"providedExports":true}},"./node_modules/lodash/_baseMatches.js":{"id":425,"buildMeta":{"providedExports":true}},"./node_modules/lodash/_baseIsMatch.js":{"id":426,"buildMeta":{"providedExports":true}},"./node_modules/lodash/_listCacheClear.js":{"id":427,"buildMeta":{"providedExports":true}},"./node_modules/lodash/_listCacheDelete.js":{"id":428,"buildMeta":{"providedExports":true}},"./node_modules/lodash/_listCacheGet.js":{"id":429,"buildMeta":{"providedExports":true}},"./node_modules/lodash/_listCacheHas.js":{"id":430,"buildMeta":{"providedExports":true}},"./node_modules/lodash/_listCacheSet.js":{"id":431,"buildMeta":{"providedExports":true}},"./node_modules/lodash/_stackClear.js":{"id":432,"buildMeta":{"providedExports":true}},"./node_modules/lodash/_stackDelete.js":{"id":433,"buildMeta":{"providedExports":true}},"./node_modules/lodash/_stackGet.js":{"id":434,"buildMeta":{"providedExports":true}},"./node_modules/lodash/_stackHas.js":{"id":435,"buildMeta":{"providedExports":true}},"./node_modules/lodash/_stackSet.js":{"id":436,"buildMeta":{"providedExports":true}},"./node_modules/lodash/_baseIsNative.js":{"id":437,"buildMeta":{"providedExports":true}},"./node_modules/lodash/_isMasked.js":{"id":438,"buildMeta":{"providedExports":true}},"./node_modules/lodash/_coreJsData.js":{"id":439,"buildMeta":{"providedExports":true}},"./node_modules/lodash/_getValue.js":{"id":440,"buildMeta":{"providedExports":true}},"./node_modules/lodash/_mapCacheClear.js":{"id":441,"buildMeta":{"providedExports":true}},"./node_modules/lodash/_Hash.js":{"id":442,"buildMeta":{"providedExports":true}},"./node_modules/lodash/_hashClear.js":{"id":443,"buildMeta":{"providedExports":true}},"./node_modules/lodash/_hashDelete.js":{"id":444,"buildMeta":{"providedExports":true}},"./node_modules/lodash/_hashGet.js":{"id":445,"buildMeta":{"providedExports":true}},"./node_modules/lodash/_hashHas.js":{"id":446,"buildMeta":{"providedExports":true}},"./node_modules/lodash/_hashSet.js":{"id":447,"buildMeta":{"providedExports":true}},"./node_modules/lodash/_mapCacheDelete.js":{"id":448,"buildMeta":{"providedExports":true}},"./node_modules/lodash/_isKeyable.js":{"id":449,"buildMeta":{"providedExports":true}},"./node_modules/lodash/_mapCacheGet.js":{"id":450,"buildMeta":{"providedExports":true}},"./node_modules/lodash/_mapCacheHas.js":{"id":451,"buildMeta":{"providedExports":true}},"./node_modules/lodash/_mapCacheSet.js":{"id":452,"buildMeta":{"providedExports":true}},"./node_modules/lodash/_baseIsEqualDeep.js":{"id":453,"buildMeta":{"providedExports":true}},"./node_modules/lodash/_SetCache.js":{"id":454,"buildMeta":{"providedExports":true}},"./node_modules/lodash/_setCacheAdd.js":{"id":455,"buildMeta":{"providedExports":true}},"./node_modules/lodash/_setCacheHas.js":{"id":456,"buildMeta":{"providedExports":true}},"./node_modules/lodash/_arraySome.js":{"id":457,"buildMeta":{"providedExports":true}},"./node_modules/lodash/_cacheHas.js":{"id":458,"buildMeta":{"providedExports":true}},"./node_modules/lodash/_equalByTag.js":{"id":459,"buildMeta":{"providedExports":true}},"./node_modules/lodash/_Uint8Array.js":{"id":460,"buildMeta":{"providedExports":true}},"./node_modules/lodash/_mapToArray.js":{"id":461,"buildMeta":{"providedExports":true}},"./node_modules/lodash/_setToArray.js":{"id":462,"buildMeta":{"providedExports":true}},"./node_modules/lodash/_equalObjects.js":{"id":463,"buildMeta":{"providedExports":true}},"./node_modules/lodash/_getAllKeys.js":{"id":464,"buildMeta":{"providedExports":true}},"./node_modules/lodash/_baseGetAllKeys.js":{"id":465,"buildMeta":{"providedExports":true}},"./node_modules/lodash/_arrayPush.js":{"id":466,"buildMeta":{"providedExports":true}},"./node_modules/lodash/_getSymbols.js":{"id":467,"buildMeta":{"providedExports":true}},"./node_modules/lodash/stubArray.js":{"id":468,"buildMeta":{"providedExports":true}},"./node_modules/lodash/_getTag.js":{"id":469,"buildMeta":{"providedExports":true}},"./node_modules/lodash/_DataView.js":{"id":470,"buildMeta":{"providedExports":true}},"./node_modules/lodash/_Promise.js":{"id":471,"buildMeta":{"providedExports":true}},"./node_modules/lodash/_Set.js":{"id":472,"buildMeta":{"providedExports":true}},"./node_modules/lodash/_WeakMap.js":{"id":473,"buildMeta":{"providedExports":true}},"./node_modules/lodash/_getMatchData.js":{"id":474,"buildMeta":{"providedExports":true}},"./node_modules/lodash/_baseMatchesProperty.js":{"id":475,"buildMeta":{"providedExports":true}},"./node_modules/lodash/get.js":{"id":476,"buildMeta":{"providedExports":true}},"./node_modules/lodash/_stringToPath.js":{"id":477,"buildMeta":{"providedExports":true}},"./node_modules/lodash/_memoizeCapped.js":{"id":478,"buildMeta":{"providedExports":true}},"./node_modules/lodash/memoize.js":{"id":479,"buildMeta":{"providedExports":true}},"./node_modules/lodash/hasIn.js":{"id":480,"buildMeta":{"providedExports":true}},"./node_modules/lodash/_baseHasIn.js":{"id":481,"buildMeta":{"providedExports":true}},"./node_modules/lodash/_hasPath.js":{"id":482,"buildMeta":{"providedExports":true}},"./node_modules/lodash/property.js":{"id":483,"buildMeta":{"providedExports":true}},"./node_modules/lodash/_baseProperty.js":{"id":484,"buildMeta":{"providedExports":true}},"./node_modules/lodash/_basePropertyDeep.js":{"id":485,"buildMeta":{"providedExports":true}},"./node_modules/lodash/trim.js":{"id":486,"buildMeta":{"providedExports":true}},"./node_modules/lodash/_castSlice.js":{"id":487,"buildMeta":{"providedExports":true}},"./node_modules/lodash/_baseSlice.js":{"id":488,"buildMeta":{"providedExports":true}},"./node_modules/lodash/_charsEndIndex.js":{"id":489,"buildMeta":{"providedExports":true}},"./node_modules/lodash/_baseFindIndex.js":{"id":490,"buildMeta":{"providedExports":true}},"./node_modules/lodash/_baseIsNaN.js":{"id":491,"buildMeta":{"providedExports":true}},"./node_modules/lodash/_strictIndexOf.js":{"id":492,"buildMeta":{"providedExports":true}},"./node_modules/lodash/_charsStartIndex.js":{"id":493,"buildMeta":{"providedExports":true}},"./node_modules/lodash/_stringToArray.js":{"id":494,"buildMeta":{"providedExports":true}},"./node_modules/lodash/_asciiToArray.js":{"id":495,"buildMeta":{"providedExports":true}},"./node_modules/lodash/_hasUnicode.js":{"id":496,"buildMeta":{"providedExports":true}},"./node_modules/lodash/_unicodeToArray.js":{"id":497,"buildMeta":{"providedExports":true}},"./node_modules/react-css-modules/dist/generateAppendClassName.js":{"id":498,"buildMeta":{"providedExports":true}},"./node_modules/react-css-modules/dist/SimpleMap.js":{"id":499,"buildMeta":{"providedExports":true}},"./node_modules/react-css-modules/dist/wrapStatelessFunction.js":{"id":500,"buildMeta":{"providedExports":true}},"./node_modules/lodash/assign.js":{"id":501,"buildMeta":{"providedExports":true}},"./node_modules/lodash/_copyObject.js":{"id":502,"buildMeta":{"providedExports":true}},"./node_modules/lodash/_createAssigner.js":{"id":503,"buildMeta":{"providedExports":true}},"./node_modules/lodash/_baseRest.js":{"id":504,"buildMeta":{"providedExports":true}},"./node_modules/lodash/_overRest.js":{"id":505,"buildMeta":{"providedExports":true}},"./node_modules/lodash/_apply.js":{"id":506,"buildMeta":{"providedExports":true}},"./node_modules/lodash/_setToString.js":{"id":507,"buildMeta":{"providedExports":true}},"./node_modules/lodash/_baseSetToString.js":{"id":508,"buildMeta":{"providedExports":true}},"./node_modules/lodash/constant.js":{"id":509,"buildMeta":{"providedExports":true}},"./node_modules/lodash/_shortOut.js":{"id":510,"buildMeta":{"providedExports":true}},"./node_modules/lodash/_isIterateeCall.js":{"id":511,"buildMeta":{"providedExports":true}},"./node_modules/react-css-modules/dist/makeConfiguration.js":{"id":512,"buildMeta":{"providedExports":true}},"./node_modules/lodash/includes.js":{"id":513,"buildMeta":{"providedExports":true}},"./node_modules/lodash/isString.js":{"id":514,"buildMeta":{"providedExports":true}},"./node_modules/lodash/toInteger.js":{"id":515,"buildMeta":{"providedExports":true}},"./node_modules/lodash/toFinite.js":{"id":516,"buildMeta":{"providedExports":true}},"./node_modules/lodash/toNumber.js":{"id":517,"buildMeta":{"providedExports":true}},"./node_modules/lodash/values.js":{"id":518,"buildMeta":{"providedExports":true}},"./node_modules/lodash/_baseValues.js":{"id":519,"buildMeta":{"providedExports":true}},"./node_modules/lodash/isBoolean.js":{"id":520,"buildMeta":{"providedExports":true}},"./node_modules/lodash/isUndefined.js":{"id":521,"buildMeta":{"providedExports":true}},"./node_modules/mobx-react/dist/mobxreact.esm.js":{"id":522,"buildMeta":{"exportsType":"namespace","providedExports":["Observer","isObserverBatched","isUsingStaticRendering","observerBatching","observerBatchingOptOut","useAsObservableSource","useLocalStore","useObserver","useStaticRendering","MobXProviderContext","PropTypes","Provider","disposeOnUnmount","inject","observer"]}}}}